{
    "GNEMS_alternate_1680460998.0421472": {
        "clouds": {
            "sc": 0.0,
            "vi": 1.0,
            "pri": 0.0,
            "miou": 0.0
        },
        "noise_0.5": {
            "sc": 0.0,
            "vi": 100.0,
            "pri": 0.0,
            "miou": 0.0
        },
        "noise_1.0": {
            "sc": 0.0,
            "vi": 100.0,
            "pri": 0.0,
            "miou": 0.0
        },
        "noise_2.0": {
            "sc": 0.0,
            "vi": 100.0,
            "pri": 0.0,
            "miou": 0.0
        },
        "noise_4.0": {
            "sc": 0.0,
            "vi": 100.0,
            "pri": 0.0,
            "miou": 0.0
        },
        "noise_8.0": {
            "sc": 0.0,
            "vi": 100.0,
            "pri": 0.0,
            "miou": 0.0
        },
        "texture": {
            "sc": 0.0,
            "vi": 100.0,
            "pri": 0.0,
            "miou": 0.0
        },
        "all": {
            "sc": 0.0,
            "vi": 80.2,
            "pri": 0.0,
            "miou": 0.0
        }
    },
    "GNEMS_alternate_1680466740.163753": {
        "clouds": {
            "sc": 0.0,
            "vi": 1.0,
            "pri": 0.0,
            "miou": 0.0
        },
        "noise_0.5": {
            "sc": 0.0,
            "vi": 100.0,
            "pri": 0.0,
            "miou": 0.0
        },
        "noise_1.0": {
            "sc": 0.0,
            "vi": 100.0,
            "pri": 0.0,
            "miou": 0.0
        },
        "noise_2.0": {
            "sc": 0.0,
            "vi": 100.0,
            "pri": 0.0,
            "miou": 0.0
        },
        "noise_4.0": {
            "sc": 0.0,
            "vi": 100.0,
            "pri": 0.0,
            "miou": 0.0
        },
        "noise_8.0": {
            "sc": 0.0,
            "vi": 100.0,
            "pri": 0.0,
            "miou": 0.0
        },
        "texture": {
            "sc": 0.0,
            "vi": 100.0,
            "pri": 0.0,
            "miou": 0.0
        },
        "all": {
            "sc": 0.0,
            "vi": 80.2,
            "pri": 0.0,
            "miou": 0.0
        }
    },
    "GNEMS_hyperset3": {
        "clouds": {
            "sc": 0.6832075829710755,
            "vi": 0.42842619556900374,
            "pri": 0.33801342437590665,
            "miou": 0.3961171047433324
        },
        "noise_0.5": {
            "sc": 0.7567238229938877,
            "vi": 0.4197821597937782,
            "pri": 0.5003570228835676,
            "miou": 0.39719679142026576
        },
        "noise_1.0": {
            "sc": 0.7249389647324929,
            "vi": 0.3963059145954252,
            "pri": 0.430934254401748,
            "miou": 0.3726839071100886
        },
        "noise_2.0": {
            "sc": 0.6666684630738043,
            "vi": 0.36785857627705665,
            "pri": 0.3011601927684615,
            "miou": 0.36906524062596935
        },
        "noise_4.0": {
            "sc": 0.6107941681943063,
            "vi": 0.2512427020039118,
            "pri": 0.14324468863000503,
            "miou": 0.31177612507632513
        },
        "noise_8.0": {
            "sc": 0.5770405668339118,
            "vi": 0.19719304109660124,
            "pri": 0.06003074366507315,
            "miou": 0.29128704813302564
        },
        "texture": {
            "sc": 0.5589472176654423,
            "vi": 0.34577464355654614,
            "pri": 0.07245736191423764,
            "miou": 0.31086081587697245
        },
        "all": {
            "sc": 0.6053435398082414,
            "vi": 0.3667217405031398,
            "pri": 0.17130914057741622,
            "miou": 0.3395529586000438
        }
    },
    "GNEMS_larger_patches": {
        "clouds": {
            "sc": 0.6784896990826831,
            "vi": 0.4449940876731043,
            "pri": 0.3120672636624747,
            "miou": 0.37008592421105363
        },
        "noise_0.5": {
            "sc": 0.7407066796486861,
            "vi": 0.4300402964104981,
            "pri": 0.47035725732337547,
            "miou": 0.4157338741426381
        },
        "noise_1.0": {
            "sc": 0.737775001252643,
            "vi": 0.4403890736160959,
            "pri": 0.4649544983873337,
            "miou": 0.36923209718375216
        },
        "noise_2.0": {
            "sc": 0.7016571809214107,
            "vi": 0.45308011154518735,
            "pri": 0.38540440646449703,
            "miou": 0.39532053786340116
        },
        "noise_4.0": {
            "sc": 0.6743600662589707,
            "vi": 0.4490001402381839,
            "pri": 0.33005206201301107,
            "miou": 0.3785328872585164
        },
        "noise_8.0": {
            "sc": 0.624678578221582,
            "vi": 0.36262139274562655,
            "pri": 0.19920892362123505,
            "miou": 0.31456098541158706
        },
        "texture": {
            "sc": 0.5541248472804479,
            "vi": 0.34030773068266384,
            "pri": 0.06433182026378122,
            "miou": 0.29921418328668975
        },
        "all": {
            "sc": 0.6085042843690875,
            "vi": 0.38379947825325667,
            "pri": 0.17809342618366308,
            "miou": 0.3326098023869048
        }
    },
    "GNEMS_lower_stride": {
        "clouds": {
            "sc": 0.6669271837707711,
            "vi": 0.4599948226305248,
            "pri": 0.32036852326029347,
            "miou": 0.4112025216858214
        },
        "noise_0.5": {
            "sc": 0.9402564256208139,
            "vi": 0.16921727141371568,
            "pri": 0.8808015580570223,
            "miou": 0.5353526962016699
        },
        "noise_1.0": {
            "sc": 0.9366730125309405,
            "vi": 0.18232271168830164,
            "pri": 0.8729931195345002,
            "miou": 0.5488277670872141
        },
        "noise_2.0": {
            "sc": 0.8674154960923695,
            "vi": 0.3368644792912011,
            "pri": 0.7380294988579514,
            "miou": 0.4545222716454759
        },
        "noise_4.0": {
            "sc": 0.7880515196947488,
            "vi": 0.48536456391476585,
            "pri": 0.5886727485037919,
            "miou": 0.445373092912565
        },
        "noise_8.0": {
            "sc": 0.7161936975557142,
            "vi": 0.5937214027419448,
            "pri": 0.4646512448642809,
            "miou": 0.40343525760444265
        },
        "texture": {
            "sc": 0.5769802794618994,
            "vi": 0.4898883879777967,
            "pri": 0.16009384005954166,
            "miou": 0.3387841785916061
        },
        "all": {
            "sc": 0.6530567036497679,
            "vi": 0.4533048931710232,
            "pri": 0.30773590845937393,
            "miou": 0.3764154658212231
        }
    },
    "GNEMS_more_slic_segments": {
        "clouds": {
            "sc": 0.6682345256068816,
            "vi": 0.4665106748290755,
            "pri": 0.3256240758674887,
            "miou": 0.3723814902301747
        },
        "noise_0.5": {
            "sc": 0.9424356947699584,
            "vi": 0.16542672379070036,
            "pri": 0.8854595905230018,
            "miou": 0.5389097016537288
        },
        "noise_1.0": {
            "sc": 0.9342021093227862,
            "vi": 0.1861412678936742,
            "pri": 0.8688875099806804,
            "miou": 0.47429098620381877
        },
        "noise_2.0": {
            "sc": 0.8545457501690361,
            "vi": 0.3549639132933058,
            "pri": 0.716678085197467,
            "miou": 0.4243800945571039
        },
        "noise_4.0": {
            "sc": 0.7740045486819358,
            "vi": 0.501331662081262,
            "pri": 0.5641747559564783,
            "miou": 0.3656217026918298
        },
        "noise_8.0": {
            "sc": 0.6690901715919548,
            "vi": 0.6482122705164223,
            "pri": 0.3875193593589087,
            "miou": 0.3383209927094102
        },
        "texture": {
            "sc": 0.5699920569853788,
            "vi": 0.5176666417328292,
            "pri": 0.15680975203203776,
            "miou": 0.3338137651472219
        },
        "all": {
            "sc": 0.6465512893464108,
            "vi": 0.4748949026641737,
            "pri": 0.3025462834322138,
            "miou": 0.3596405760457888
        }
    },
    "GNEMS_higher_sigma": {
        "clouds": {
            "sc": 0.6592754503835339,
            "vi": 0.45049688475642335,
            "pri": 0.2986453673509877,
            "miou": 0.365967519113642
        },
        "noise_0.5": {
            "sc": 0.9388583721727568,
            "vi": 0.1701079042847704,
            "pri": 0.8783410540795331,
            "miou": 0.4954184611982377
        },
        "noise_1.0": {
            "sc": 0.92863384184636,
            "vi": 0.19679382035616247,
            "pri": 0.8589784299125961,
            "miou": 0.4916611250727281
        },
        "noise_2.0": {
            "sc": 0.8631909158121949,
            "vi": 0.34303103829989134,
            "pri": 0.7322220638291691,
            "miou": 0.4599356495731032
        },
        "noise_4.0": {
            "sc": 0.7803855954313619,
            "vi": 0.49046017184265056,
            "pri": 0.5769250024783066,
            "miou": 0.36051096206175653
        },
        "noise_8.0": {
            "sc": 0.7177657527214667,
            "vi": 0.5910989020832778,
            "pri": 0.46345502577040765,
            "miou": 0.3174297958994759
        },
        "texture": {
            "sc": 0.58006386543832,
            "vi": 0.4892700298445955,
            "pri": 0.16469793478171682,
            "miou": 0.333119580314327
        },
        "all": {
            "sc": 0.6525315925021378,
            "vi": 0.4522676025180202,
            "pri": 0.3049922471050614,
            "miou": 0.3650523819259452
        }
    },
    "GNEMS_more_filters": {
        "clouds": {
            "sc": 0.6818719829190496,
            "vi": 0.45211526949831227,
            "pri": 0.34072312343565586,
            "miou": 0.43223848972555
        },
        "noise_0.5": {
            "sc": 0.9400460768354575,
            "vi": 0.1705420781917364,
            "pri": 0.879784528341772,
            "miou": 0.4398037024710142
        },
        "noise_1.0": {
            "sc": 0.9370327366446263,
            "vi": 0.18325189625482718,
            "pri": 0.8739817406438697,
            "miou": 0.5114594789213472
        },
        "noise_2.0": {
            "sc": 0.8667150507654742,
            "vi": 0.33804032638786286,
            "pri": 0.7376727705194597,
            "miou": 0.464656274262159
        },
        "noise_4.0": {
            "sc": 0.7754389739314554,
            "vi": 0.4985885665783133,
            "pri": 0.5685186052344338,
            "miou": 0.3753795104632941
        },
        "noise_8.0": {
            "sc": 0.6904097663944176,
            "vi": 0.6251887068540988,
            "pri": 0.41750958525081006,
            "miou": 0.36160733345532287
        },
        "texture": {
            "sc": 0.5780166779670436,
            "vi": 0.486787717226042,
            "pri": 0.1627883674419408,
            "miou": 0.3299787264642548
        },
        "all": {
            "sc": 0.656527413517131,
            "vi": 0.45010374951286025,
            "pri": 0.31335219925618757,
            "miou": 0.3773661886760946
        }
    },
    "GNEMS_hyperset1": {
        "clouds": {
            "sc": 0.6810918350292533,
            "vi": 0.425081329291762,
            "pri": 0.29555566258146293,
            "miou": 0.38017766704405753
        },
        "noise_0.5": {
            "sc": 0.7468305214752932,
            "vi": 0.428607538774057,
            "pri": 0.4787087366640844,
            "miou": 0.39363595338458474
        },
        "noise_1.0": {
            "sc": 0.7213615775863427,
            "vi": 0.38001122368578016,
            "pri": 0.41594495060608416,
            "miou": 0.3772708211174201
        },
        "noise_2.0": {
            "sc": 0.6655236108258913,
            "vi": 0.3607403804766315,
            "pri": 0.2901424927067092,
            "miou": 0.36829961753805895
        },
        "noise_4.0": {
            "sc": 0.6123258850086597,
            "vi": 0.25265208115981325,
            "pri": 0.14451243984831302,
            "miou": 0.2872667403469251
        },
        "noise_8.0": {
            "sc": 0.572941137806857,
            "vi": 0.18984084125029155,
            "pri": 0.04982948684055221,
            "miou": 0.2822915818255778
        },
        "texture": {
            "sc": 0.5557111694704336,
            "vi": 0.34677651133886594,
            "pri": 0.07130374291428883,
            "miou": 0.3077488520834314
        },
        "all": {
            "sc": 0.6027497908532891,
            "vi": 0.3652302487569983,
            "pri": 0.15992187680620776,
            "miou": 0.3343447681664822
        }
    },
    "GNEMS_less_slic_segments": {
        "clouds": {
            "sc": 0.6645085527322837,
            "vi": 0.435026856492912,
            "pri": 0.2906840410691675,
            "miou": 0.37684338064732253
        },
        "noise_0.5": {
            "sc": 0.9406681092333016,
            "vi": 0.16857764927598434,
            "pri": 0.881354604581275,
            "miou": 0.4911682709889081
        },
        "noise_1.0": {
            "sc": 0.9270563046168643,
            "vi": 0.1986974995611329,
            "pri": 0.8565062677806397,
            "miou": 0.4705199354527401
        },
        "noise_2.0": {
            "sc": 0.8588003972022361,
            "vi": 0.34937744550800365,
            "pri": 0.726746111604113,
            "miou": 0.4569452773403481
        },
        "noise_4.0": {
            "sc": 0.79249662754466,
            "vi": 0.47767180790085473,
            "pri": 0.5955883933524149,
            "miou": 0.425694738509
        },
        "noise_8.0": {
            "sc": 0.6609125809186169,
            "vi": 0.6591587230997049,
            "pri": 0.37608859842293835,
            "miou": 0.3848801892460665
        },
        "texture": {
            "sc": 0.5697479015583556,
            "vi": 0.5058586736089309,
            "pri": 0.15126199711088797,
            "miou": 0.3312670627605508
        },
        "all": {
            "sc": 0.6465105309219173,
            "vi": 0.4603960645655417,
            "pri": 0.29424322880118886,
            "miou": 0.3655179692538646
        }
    },
    "GNEMS_hyperset2": {
        "clouds": {
            "sc": 0.6856022237890478,
            "vi": 0.43405830692699554,
            "pri": 0.323414460792182,
            "miou": 0.3948546502463007
        },
        "noise_0.5": {
            "sc": 0.9507089860383056,
            "vi": 0.15067548631272965,
            "pri": 0.9007519241485984,
            "miou": 0.49225304522626234
        },
        "noise_1.0": {
            "sc": 0.9463879441732104,
            "vi": 0.16461093683199546,
            "pri": 0.8919033310666333,
            "miou": 0.4818949882797231
        },
        "noise_2.0": {
            "sc": 0.8858932826722121,
            "vi": 0.30888333607841856,
            "pri": 0.7713220956865131,
            "miou": 0.48134117048294583
        },
        "noise_4.0": {
            "sc": 0.8233135773241591,
            "vi": 0.42967691193330304,
            "pri": 0.646881996815865,
            "miou": 0.4453941952855389
        },
        "noise_8.0": {
            "sc": 0.7510799472489937,
            "vi": 0.5460109120677965,
            "pri": 0.5182500718357826,
            "miou": 0.40506065704074856
        },
        "texture": {
            "sc": 0.5883155504371573,
            "vi": 0.44724197458985265,
            "pri": 0.17439008028024539,
            "miou": 0.3221089903554993
        },
        "all": {
            "sc": 0.6672884315545463,
            "vi": 0.41693351335499446,
            "pri": 0.3235813594638862,
            "miou": 0.3685045583591489
        }
    },
    "GNEMS_lower_sigma": {
        "clouds": {
            "sc": 0.6611296732901912,
            "vi": 0.4559213180183802,
            "pri": 0.29715674809116116,
            "miou": 0.41526613521179234
        },
        "noise_0.5": {
            "sc": 0.9422153308864962,
            "vi": 0.1664732343462974,
            "pri": 0.8840228021320489,
            "miou": 0.467324391816432
        },
        "noise_1.0": {
            "sc": 0.9358274586776323,
            "vi": 0.18351999282304698,
            "pri": 0.871256549244974,
            "miou": 0.45202820952138417
        },
        "noise_2.0": {
            "sc": 0.8657752367966766,
            "vi": 0.3405685948390976,
            "pri": 0.7363040792981549,
            "miou": 0.49898325669732974
        },
        "noise_4.0": {
            "sc": 0.7758042567496273,
            "vi": 0.5020832019728649,
            "pri": 0.568711441915544,
            "miou": 0.37195696915396614
        },
        "noise_8.0": {
            "sc": 0.690857632836569,
            "vi": 0.6221301108746395,
            "pri": 0.4238306259300828,
            "miou": 0.30648989142582417
        },
        "texture": {
            "sc": 0.5623470442640371,
            "vi": 0.5177220652496253,
            "pri": 0.14442280115487088,
            "miou": 0.32728658896838403
        },
        "all": {
            "sc": 0.6427892085757957,
            "vi": 0.4699312217212707,
            "pri": 0.29334584617078574,
            "miou": 0.3792218317628549
        }
    },
    "GNEMS_lower_lambda": {
        "clouds": {
            "sc": 0.6712406700532653,
            "vi": 0.4384244649292608,
            "pri": 0.3041649956510578,
            "miou": 0.4066874154894007
        },
        "noise_0.5": {
            "sc": 0.9490341473004117,
            "vi": 0.15321267937527636,
            "pri": 0.8972133941768002,
            "miou": 0.4682543007041522
        },
        "noise_1.0": {
            "sc": 0.9466764936305252,
            "vi": 0.16619345867389376,
            "pri": 0.8926761942611288,
            "miou": 0.46453549654766946
        },
        "noise_2.0": {
            "sc": 0.8793204673375824,
            "vi": 0.31690278183270015,
            "pri": 0.7593590301716683,
            "miou": 0.40009980727123035
        },
        "noise_4.0": {
            "sc": 0.8177528918742973,
            "vi": 0.4372098773996821,
            "pri": 0.6384763216725441,
            "miou": 0.43173171916819064
        },
        "noise_8.0": {
            "sc": 0.7407088188784127,
            "vi": 0.5557246484670104,
            "pri": 0.5007324691606685,
            "miou": 0.3960442870183035
        },
        "texture": {
            "sc": 0.5804099045912506,
            "vi": 0.4635741489280982,
            "pri": 0.16116002525927128,
            "miou": 0.3248920597758255
        },
        "all": {
            "sc": 0.65835817023292,
            "vi": 0.4292099387092511,
            "pri": 0.30940082032010796,
            "miou": 0.3562926804176215
        }
    },
    "GNEMS_hyperset5": {
        "clouds": {
            "sc": 0.6812157828743128,
            "vi": 0.4277266842009543,
            "pri": 0.3156948694474838,
            "miou": 0.3860451671824091
        },
        "noise_0.5": {
            "sc": 0.9484545785878206,
            "vi": 0.15545905387737402,
            "pri": 0.8963139541178091,
            "miou": 0.4996239521685175
        },
        "noise_1.0": {
            "sc": 0.9422892815823172,
            "vi": 0.17168796329412456,
            "pri": 0.8831238983809374,
            "miou": 0.5191121728168053
        },
        "noise_2.0": {
            "sc": 0.8856161837241792,
            "vi": 0.309737599141914,
            "pri": 0.7708150544877854,
            "miou": 0.47377057147219187
        },
        "noise_4.0": {
            "sc": 0.8159552129299654,
            "vi": 0.4397534137542759,
            "pri": 0.6358270944993326,
            "miou": 0.3742972910729089
        },
        "noise_8.0": {
            "sc": 0.7380866863915803,
            "vi": 0.5603049055486211,
            "pri": 0.4977881841564006,
            "miou": 0.36967674817442503
        },
        "texture": {
            "sc": 0.584475201459426,
            "vi": 0.44571837571516815,
            "pri": 0.1634319804475312,
            "miou": 0.3228373213964281
        },
        "all": {
            "sc": 0.6640515141953541,
            "vi": 0.41492388209767456,
            "pri": 0.31536117305557254,
            "miou": 0.3656655405687771
        }
    },
    "GNEMS_higher_stride": {
        "clouds": {
            "sc": 0.6716602088894112,
            "vi": 0.45331596231641236,
            "pri": 0.31837497900609757,
            "miou": 0.4047379532355412
        },
        "noise_0.5": {
            "sc": 0.9308601291352161,
            "vi": 0.18618782160105812,
            "pri": 0.8617496686739505,
            "miou": 0.46578732630485575
        },
        "noise_1.0": {
            "sc": 0.9147971559952195,
            "vi": 0.21554039288977792,
            "pri": 0.8322433133639229,
            "miou": 0.4683741562740522
        },
        "noise_2.0": {
            "sc": 0.8464608564899226,
            "vi": 0.36943008411338396,
            "pri": 0.6998185575290287,
            "miou": 0.4874558961193153
        },
        "noise_4.0": {
            "sc": 0.7603123298109173,
            "vi": 0.5142119448860598,
            "pri": 0.5406501785901356,
            "miou": 0.4492265521099086
        },
        "noise_8.0": {
            "sc": 0.6303835491829382,
            "vi": 0.6965278030279367,
            "pri": 0.322787480126823,
            "miou": 0.4219500570824346
        },
        "texture": {
            "sc": 0.5619778102783747,
            "vi": 0.5024134418118672,
            "pri": 0.14079277130714782,
            "miou": 0.3234149564483486
        },
        "all": {
            "sc": 0.6408108992428916,
            "vi": 0.4659972743730796,
            "pri": 0.2881143700913139,
            "miou": 0.3724877437399804
        }
    },
    "GNEMS_less_filters": {
        "clouds": {
            "sc": 0.6630796580522169,
            "vi": 0.4620549065329271,
            "pri": 0.30454343043882215,
            "miou": 0.38635929546078124
        },
        "noise_0.5": {
            "sc": 0.9390406103114952,
            "vi": 0.17129202351933773,
            "pri": 0.8781722346446814,
            "miou": 0.5241262660655358
        },
        "noise_1.0": {
            "sc": 0.93529084308746,
            "vi": 0.18650366934536133,
            "pri": 0.8704733776057958,
            "miou": 0.4929291883394924
        },
        "noise_2.0": {
            "sc": 0.870726972198723,
            "vi": 0.33341310945684055,
            "pri": 0.7434099068850952,
            "miou": 0.4787506894315682
        },
        "noise_4.0": {
            "sc": 0.7880921736550837,
            "vi": 0.4820365620082474,
            "pri": 0.5916973515854111,
            "miou": 0.3831711563056086
        },
        "noise_8.0": {
            "sc": 0.6960473253971675,
            "vi": 0.6162128773475216,
            "pri": 0.4304042089371565,
            "miou": 0.3415696238541074
        },
        "texture": {
            "sc": 0.5701131894929387,
            "vi": 0.49975930359621373,
            "pri": 0.15222579981892628,
            "miou": 0.3332900521857371
        },
        "all": {
            "sc": 0.6488292397459512,
            "vi": 0.4589491853556817,
            "pri": 0.3009261473561393,
            "miou": 0.3729960282899122
        }
    },
    "GNEMS": {
        "clouds": {
            "sc": 0.6726222257671248,
            "vi": 0.44780838585324495,
            "pri": 0.30853330065609685,
            "miou": 0.38897334204576073
        },
        "noise_0.5": {
            "sc": 0.9460470396043943,
            "vi": 0.1575720729591387,
            "pri": 0.891133500054039,
            "miou": 0.5182838981702717
        },
        "noise_1.0": {
            "sc": 0.9320957919057311,
            "vi": 0.19117327517731805,
            "pri": 0.8652258089160076,
            "miou": 0.46616616529114485
        },
        "noise_2.0": {
            "sc": 0.8621929864271656,
            "vi": 0.34712401212421123,
            "pri": 0.7306992467981793,
            "miou": 0.426564243998116
        },
        "noise_4.0": {
            "sc": 0.7839567506868209,
            "vi": 0.4901652671513672,
            "pri": 0.5834974497663052,
            "miou": 0.45637964861219693
        },
        "noise_8.0": {
            "sc": 0.6965041871168557,
            "vi": 0.6190705292692531,
            "pri": 0.4295327518612123,
            "miou": 0.39206185247314007
        },
        "texture": {
            "sc": 0.5711855315629683,
            "vi": 0.48274472191033446,
            "pri": 0.15010081052200322,
            "miou": 0.3286892106805458
        },
        "all": {
            "sc": 0.649674361376639,
            "vi": 0.448633312741692,
            "pri": 0.2979069958040571,
            "miou": 0.3603210436171028
        }
    },
    "GNEMS_hyperset4": {
        "clouds": {
            "sc": 0.6812570344497682,
            "vi": 0.4259689397666029,
            "pri": 0.3180803986989804,
            "miou": 0.3958360142588663
        },
        "noise_0.5": {
            "sc": 0.9484789235132456,
            "vi": 0.15632166944273707,
            "pri": 0.8961866135010912,
            "miou": 0.4617130335333093
        },
        "noise_1.0": {
            "sc": 0.9444007226168447,
            "vi": 0.16907564864296523,
            "pri": 0.8885245788067921,
            "miou": 0.48400250311752785
        },
        "noise_2.0": {
            "sc": 0.8836033619365796,
            "vi": 0.3113908914829101,
            "pri": 0.766662606825354,
            "miou": 0.4677539017523459
        },
        "noise_4.0": {
            "sc": 0.819766539569917,
            "vi": 0.4360495425289318,
            "pri": 0.6414548779020491,
            "miou": 0.45389566714264673
        },
        "noise_8.0": {
            "sc": 0.7512519613642504,
            "vi": 0.5421046229586838,
            "pri": 0.5203160912110618,
            "miou": 0.365556346370187
        },
        "texture": {
            "sc": 0.58393667746994,
            "vi": 0.43586600632716327,
            "pri": 0.1590207430598732,
            "miou": 0.3227653714002932
        },
        "all": {
            "sc": 0.6633340857592336,
            "vi": 0.4089915700462005,
            "pri": 0.3123610469407908,
            "miou": 0.3663772060424184
        }
    },
    "GNEMS_higher_lambda": {
        "clouds": {
            "sc": 0.6723848997633626,
            "vi": 0.46195451220239026,
            "pri": 0.32808770097473194,
            "miou": 0.41733922585918437
        },
        "noise_0.5": {
            "sc": 0.8834343983557947,
            "vi": 0.26370604924623664,
            "pri": 0.7804017944860266,
            "miou": 0.47368428477027574
        },
        "noise_1.0": {
            "sc": 0.8019889865389296,
            "vi": 0.40019534513229155,
            "pri": 0.6404845527001404,
            "miou": 0.4989927197912728
        },
        "noise_2.0": {
            "sc": 0.7467361446741647,
            "vi": 0.5178417506925583,
            "pri": 0.5333573026577878,
            "miou": 0.45265628016914083
        },
        "noise_4.0": {
            "sc": 0.7188606308159129,
            "vi": 0.5831008485347453,
            "pri": 0.47265335903326133,
            "miou": 0.35144967770407187
        },
        "noise_8.0": {
            "sc": 0.6639908053704562,
            "vi": 0.6620283863721361,
            "pri": 0.3778322149825297,
            "miou": 0.33461121845343805
        },
        "texture": {
            "sc": 0.5630954562744795,
            "vi": 0.5802475929997399,
            "pri": 0.1574040769567732,
            "miou": 0.3370153093089676
        },
        "all": {
            "sc": 0.6216814826521931,
            "vi": 0.5441078083788338,
            "pri": 0.2667314469005679,
            "miou": 0.3762082867910456
        }
    },
    "GNEMS_smaller_patches": {
        "clouds": {
            "sc": 0.6483216515163721,
            "vi": 0.49080811564505633,
            "pri": 0.30718938732053164,
            "miou": 0.36960328681103355
        },
        "noise_0.5": {
            "sc": 0.862484538152053,
            "vi": 0.2668156809688312,
            "pri": 0.7547922947800672,
            "miou": 0.5118417647662057
        },
        "noise_1.0": {
            "sc": 0.8278752616279097,
            "vi": 0.3420115180630878,
            "pri": 0.6899535337805298,
            "miou": 0.45952406799144596
        },
        "noise_2.0": {
            "sc": 0.7596728291850059,
            "vi": 0.499177596987119,
            "pri": 0.5572645290580349,
            "miou": 0.45016646289981077
        },
        "noise_4.0": {
            "sc": 0.6742326789833861,
            "vi": 0.6425102132086992,
            "pri": 0.40233926488225386,
            "miou": 0.42357943990033
        },
        "noise_8.0": {
            "sc": 0.5658502371045844,
            "vi": 0.7847427220146118,
            "pri": 0.2262918167396621,
            "miou": 0.3704810527647574
        },
        "texture": {
            "sc": 0.5271711170554324,
            "vi": 0.7468150636120274,
            "pri": 0.15837140311101464,
            "miou": 0.3488706001799912
        },
        "all": {
            "sc": 0.5979015663735351,
            "vi": 0.6460861806936515,
            "pri": 0.2679136251423221,
            "miou": 0.3732763100501636
        }
    }
}